Metadata-Version: 1.0
Name: oreumums
Version: 0.1.5
Summary: A package for using UMS service of Oreum Corporation.
Home-page: https://api.smsrang.co.kr
Author: alghost
Author-email: alghost@moreum.co.kr
License: UNKNOWN
Platform: UNKNOWN
